{
    "menuNames": [
        "Navigationsleiste",

        "Konto",
            "Anmelden",
            "Registrieren",
        
        "Routen",
            "Starten",
            "Entfernen",
            
            "Starten",
            "Erreicht",
            "Abgeschlossen!",
        
        "Barrierefreiheit",
            "Text vergrößern",
            "Farbkontrast",
            "Schwarz & Weiß",
            "Text-zu-Sprache",
        
        "Einstellungen",
            "Legende",
            " = Ziel nicht erreicht",
            " = Ziel erreicht",
            " = Route abgeschlossen",
            "Sprache",
        
        "Unser Team",
            "Willkommen in der Welt von <i>Better Ways</i>! Wir sind fünf Schüler der Klasse 4ID des IIS A.Volta in Lodi. <br>Unsere Namen sind: Silvia Bollani, Alessandro Marano, Alexandru Quiroz, Matteo Scaratti und Linda Tessadori. <br>Unsere Website, <i>Better Ways</i>, konzentriert sich auf den Tourismus in Lodi, um die Schönheiten dieser kleinen Stadt zu entdecken. <br>Darüber hinaus setzen wir uns dafür ein, dass unsere Website nach den Standards der <i>Barrierefreiheit</i> gestaltet und entwickelt wird, um allen Besuchern ein inklusives Erlebnis zu bieten.",
        
        "Startseite",
        
        "Karte zentrieren",
        
        "Einzelner Marker",
            "Hinzufügen",
            "Entfernen",
            "Alle hinzufügen",
            "Alle entfernen",

        "Reiseroute abgeschlossen!"
    ],

    "placesNames": {
        "Schloss-Visconteo": [
            [45.312376641034014, 9.498816848941937],
            "Schloss Visconteo",
            3,
            "",
            "../img/tappe-popup/Castello_Visconteo.jpg"
        ],
        "Kirche-San-Francesco": [
            [45.314617754968054, 9.507929720552477],
            "Kirche San Francesco",
            1,
            "",
            "../img/tappe-popup/chiesa_san_francesco.jpeg"
        ],
        "Dom-von-Lodi": [
            [45.314214319510235, 9.503150096251492],
            "Dom von Lodi",
            1,
            "",
            "../img/tappe-popup/Lodi_Duomo_facciata.jpg"
        ],
        "Faustina-Sporting-Club": [
            [45.30054479572416, 9.50729370117188],
            "Faustina Sporting Club",
            5,
            "",
            "../img/tappe-popup/faustina.jpg"
        ],
        "Denkmal-für-den-Widerstand": [
            [45.31043780366223, 9.501946341831502],
            "Denkmal für den Widerstand",
            0,
            "",
            "../img/tappe-popup/monumento_alla_Resistenza.jpg"
        ],
        "Museum-der-Druckkunst": [
            [45.31796325796598, 9.502647436164928],
            "Museum der Druckkunst",
            4,
            "",
            "../img/tappe-popup/lodi_museo_della_stampa.jpg"
        ],
        "Museum-für-Musikinstrumente-&-Musik": [
            [45.30701338770822, 9.50199549913424],
            "Museum für Musikinstrumente & Musik",
            3,
            "",
            "../img/tappe-popup/museo_dello_strumento_musicale_e_della_musica.jpg"
        ],
        "Museum-von-Paolo-Gorini": [
            [45.3138348117735, 9.508056454515657],
            "Museum von Paolo Gorini",
            5,
            "",
            "../img/tappe-popup/museo-paolo-gorini-lodi.jpg"
        ],
        "Sporteinrichtung-Palacastellotti": [
            [45.297359483089814, 9.510770296119013],
            "Sporteinrichtung Palacastellotti",
            1,
            "",
            "../img/tappe-popup/palacastellotti.jpg"
        ],
        "Park-Adda-Süd": [
            [45.314040272551736, 9.498271300674975],
            "Park Adda Süd",
            2,
            "",
            "../img/tappe-popup/Parco_adda_sud.jpg"
        ],
        "Park-der-Isola-Carolina": [
            [45.315097006869266, 9.498896680791935],
            "Park der Isola Carolina",
            2,
            "",
            "../img/tappe-popup/isola_carolina.jpg"
        ],
        "Park-Villa-Braila": [
            [45.30376301489828, 9.508691843847435],
            "Park Villa Braila",
            0,
            "",
            "../img/tappe-popup/villa_Braila.jpg"
        ],
        "Stadion-Dossenina": [
            [45.30739132224016, 9.495022000717784],
            "Stadion Dossenina",
            3,
            "",
            "../img/tappe-popup/Stadio_Dossenina.jpg"
        ],
        "Theater-Alle-Vigne": [
            [45.31506910520015, 9.506154729318768],
            "Theater Alle Vigne",
            3,
            "",
            "../img/tappe-popup/Teatro-alle-Vigne.jpg"
        ],
        "Bürgerlicher-Tempel-der-Incoronata": [
            [45.31465971960593, 9.502055674244136],
            "Bürgerlicher Tempel der Incoronata",
            2,
            "",
            "../img/tappe-popup/TempioIncoronata.jpg"
        ],
        "Lodi-Turm": [
            [45.3126397552172, 9.498001343678204],
            "Lodi-Turm",
            3,
            "",
            "../img/tappe-popup/torrione.jpg"
        ],
        "Broletto-Platz": [
            [45.31452738912999, 9.50285367329064],
            "Broletto Platz",
            3,
            "",
            ""
        ],
        "Marktplatz": [
            [45.315046320365575, 9.504111225140116],
            "Marktplatz",
            4,
            "",
            ""
        ],
        "Touristenbüro": [
            [45.31457313558977, 9.502831126442807],
            "Touristenbüro",
            5,
            "",
            ""
        ],
        "Kirche-der-Magdalena": [
            [45.31835179420975, 9.504352611647226],
            "Kirche der Magdalena",
            4,
            "",
            ""
        ],
        "Laudense-Bibliothek": [
            [45.316260560309566, 9.504173325140222],
            "Laudense Bibliothek",
            4,
            "",
            ""
        ]
    },

    "itineraryNames": {
        "Schlösser": [
            "Schloss-Visconteo",
            "Lodi-Turm"
        ],
        "Religiöse Stätten": [
            "Dom-von-Lodi",
            "Bürgerlicher-Tempel-der-Incoronata",
            "Kirche-San-Francesco"
        ],
        "Ehrenmale": [
            "Denkmal-für-den-Widerstand"
        ],
        "Museen & Theater": [
            "Museum-der-Druckkunst",
            "Museum-von-Paolo-Gorini",
            "Theater-Alle-Vigne",
            "Museum-für-Musikinstrumente-&-Musik",
            "Laudense-Bibliothek"
        ],
        "Parks": [
            "Park-Adda-Süd",
            "Park-der-Isola-Carolina",
            "Park-Villa-Braila"
        ],
        "Sporteinrichtungen": [
            "Stadion-Dossenina",
            "Faustina-Sporting-Club",
            "Sporteinrichtung-Palacastellotti"
        ],
        "Piazze": [
            "Broletto-Platz",
            "Marktplatz"
        ]
    }
}